filedetect/FileDetect.py
filedetect/Formats.py
filedetect/__about__.py
filedetect/__init__.py
filedetect/cli.py
filedetect-0.1.7.dist-info/METADATA
filedetect-0.1.7.dist-info/WHEEL
filedetect-0.1.7.dist-info/entry_points.txt
filedetect-0.1.7.dist-info/licenses/LICENSE.txt
filedetect-0.1.7.dist-info/RECORD
