Metadata-Version: 2.4
Name: filedetect
Version: 0.1.7
Summary: Detects files in a directory and its subdirectories.
Project-URL: Documentation, https://github.com/Marceau-h/filedetect#readme
Project-URL: Issues, https://github.com/Marceau-h/filedetect/issues
Project-URL: Source, https://github.com/Marceau-h/filedetect
Author-email: Marceau <pypi@marceau-h.fr>
License-Expression: AGPL-3.0-or-later
License-File: LICENSE.txt
Keywords: detect,directory,file,file system,filedetect,filesystem,io,path,pathlib,subdirectory,traversal
Classifier: Development Status :: 4 - Beta
Classifier: Programming Language :: Python
Classifier: Programming Language :: Python :: 3.9
Classifier: Programming Language :: Python :: 3.10
Classifier: Programming Language :: Python :: 3.11
Classifier: Programming Language :: Python :: 3.12
Classifier: Programming Language :: Python :: 3.13
Classifier: Programming Language :: Python :: 3.14
Classifier: Programming Language :: Python :: Implementation :: CPython
Classifier: Programming Language :: Python :: Implementation :: PyPy
Requires-Python: >=3.9
